py3oauth2/errors.py
py3oauth2/message.py
py3oauth2/exceptions.py
py3oauth2/__init__.py
py3oauth2/authorizationcodegrant.py
py3oauth2/utils.py
py3oauth2/implicitgrant.py
py3oauth2/interfaces.py
py3oauth2/provider.py
py3oauth2/refreshtokengrant.py
py3oauth2-0.4.7.dist-info/METADATA
py3oauth2-0.4.7.dist-info/RECORD
py3oauth2-0.4.7.dist-info/WHEEL
py3oauth2-0.4.7.dist-info/top_level.txt
py3oauth2-0.4.7.dist-info/DESCRIPTION.rst
py3oauth2-0.4.7.dist-info/metadata.json
