Metadata-Version: 1.1
Name: py3oauth2
Version: 0.4.7
Summary: OAuth 2.0 library for Python 3.
Home-page: https://github.com/GehirnInc/py3oauth2
Author: Kohei YOSHIDA
Author-email: kohei.yoshida@gehirn.co.jp
License: The MIT License (MIT) Copyright © 2014 Kohei YOSHIDA <kohei.yoshida@gehirn.co.jp>
